sm64_binds/Sm64Game.py
sm64_binds/__init__.py
sm64_binds/buttons.py
sm64_binds/pkg/sm64_headless.us.wasm.zip.xor
sm64_binds-0.0.6.dist-info/licenses/LICENSE
sm64_binds-0.0.6.dist-info/METADATA
sm64_binds-0.0.6.dist-info/WHEEL
sm64_binds-0.0.6.dist-info/top_level.txt
sm64_binds-0.0.6.dist-info/RECORD
