Metadata-Version: 2.4
Name: sm64-binds
Version: 0.0.6
Summary: Mario 64 using WASM. Requires a US .z64 version ROM to work (8.00MB)
Author-email: Gumbo64 <gumbo64isme@proton.me>
License-Expression: MIT
Project-URL: homepage, https://github.com/Gumbo64/sm64-binds
Project-URL: repository, https://github.com/Gumbo64/sm64-binds
Classifier: Programming Language :: Python :: 3
Classifier: Operating System :: OS Independent
Requires-Python: >=3.9
License-File: LICENSE
Requires-Dist: wasmtime>=40.0.0
Dynamic: license-file
